[
  {
    "id": "general-information",
    "title": "Allgemein",
    "fields": [
      {
        "id": "name",
        "label": "Name"
      },
      {
        "id": "family",
        "label": "Familie"
      },
      {
        "id": "place-of-birth",
        "label": "Geburtsort"
      },
      {
        "id": "birthday",
        "label": "Geburtsdatum"
      },
      {
        "id": "age",
        "label": "Alter"
      },
      {
        "id": "sex",
        "label": "Geschlecht"
      },
      {
        "id": "species",
        "label": "Spezies"
      },
      {
        "id": "size",
        "label": "Größe"
      },
      {
        "id": "weight",
        "label": "Gewicht"
      },
      {
        "id": "hair-color",
        "label": "Haarfarbe"
      },
      {
        "id": "eyecolor",
        "label": "Augenfarbe"
      },
      {
        "id": "culture",
        "label": "Kultur"
      },
      {
        "id": "profession",
        "label": "Profession"
      },
      {
        "id": "title",
        "label": "Titel"
      },
      {
        "id": "social-status",
        "label": "Sozialstatus"
      },
      {
        "id": "characteristics",
        "label": "Charakteristika"
      },
      {
        "id": "other-information",
        "label": "Sonstiges"
      }
    ]
  },
  {
    "id": "attribtes",
    "title": "Attribute",
    "fields": [
      {
        "id": "courage",
        "label": "MU",
        "style": "box",
        "type": "number",
        "values": [
          1,
          2,
          3,
          4,
          5
        ]
      },
      {
        "id": "cleverness",
        "label": "KL",
        "style": "box",
        "type": "number",
        "values": [
          1,
          2,
          3,
          4,
          5
        ]
      },
      {
        "id": "intuition",
        "label": "IN",
        "style": "box",
        "type": "number",
        "values": [
          1,
          2,
          3,
          4,
          5
        ]
      },
      {
        "id": "charisma",
        "label": "CH",
        "style": "box",
        "type": "number",
        "values": [
          1,
          2,
          3,
          4,
          5
        ]
      },
      {
        "id": "dexterity",
        "label": "FF",
        "style": "box",
        "type": "number",
        "values": [
          1,
          2,
          3,
          4,
          5
        ]
      },
      {
        "id": "agility",
        "label": "GE",
        "style": "box",
        "type": "number",
        "values": [
          1,
          2,
          3,
          4,
          5
        ]
      },
      {
        "id": "constitution",
        "label": "KO",
        "style": "box",
        "type": "number",
        "values": [
          1,
          2,
          3,
          4,
          5
        ]
      },
      {
        "id": "strength",
        "label": "KK",
        "style": "box",
        "type": "number",
        "values": [
          1,
          2,
          3,
          4,
          5
        ]
      }
    ]
  },
  {
    "id": "delivered-data",
    "title": "Grundwerte",
    "fields": [
      {
        "id": "life-points",
        "label": "Lebensenergie"
      },
      {
        "id": "spirit",
        "label": "Seelenkraft"
      },
      {
        "id": "toughness",
        "label": "Zähigkeit"
      },
      {
        "id": "dodge",
        "label": "Ausweichen"
      },
      {
        "id": "initiative",
        "label": "Initiative"
      },
      {
        "id": "movement",
        "label": "Geschwindigkeit"
      }
    ]
  },
  {
    "id": "advantages",
    "title": "Vorteile",
    "fields": [
      {
        "id": "",
        "label": "test"
      }
    ]
  },
  {
    "id": "disadvantages",
    "title": "Nachteile",
    "fields": [
      {
        "id": "",
        "label": "test"
      }
    ]
  },
  {
    "id": "special-abilities",
    "title": "Sonderfertigkeiten",
    "fields": [
      {
        "id": "",
        "label": "test"
      }
    ]
  },
  {
    "id": "combat-talents",
    "title": "Kampftechniken",
    "fields": [
      {
        "id": "crossbows",
        "label": "Armbrüste"
      },
      {
        "id": "bows",
        "label": "Bögen"
      },
      {
        "id": "daggers",
        "label": "Dolche"
      },
      {
        "id": "fencing-weapons",
        "label": "Fechtwaffen"
      },
      {
        "id": "impact-weapons",
        "label": "Hiebwaffen"
      },
      {
        "id": "chain-weapons",
        "label": "Kettenwaffen"
      },
      {
        "id": "brawling",
        "label": "Raufen"
      },
      {
        "id": "shields",
        "label": "Schilde"
      },
      {
        "id": "swords",
        "label": "Schwerter"
      },
      {
        "id": "polearms",
        "label": "Stangenwaffen"
      },
      {
        "id": "thrown-weapons",
        "label": "Wurfwaffen"
      },
      {
        "id": "2h-impact-weapons",
        "label": "Zweihandhiebwaffen"
      },
      {
        "id": "2h-swords",
        "label": "Zweihandschwerter"
      }
    ]
  },
  {
    "id": "talents",
    "title": "Fertigkeiten",
    "fields": [
      {
        "id": "",
        "label": ""
      }
    ]
  },
  {
    "id": "weapons-and-armor",
    "title": "Waffen & Rüstungen",
    "fields": [
      {
        "id": "",
        "label": "test"
      }
    ]
  },
  {
    "id": "equipment",
    "title": "Ausrüstung",
    "fields": [
      {
        "id": "",
        "label": "test"
      }
    ]
  }
]